{
    "taskDefinitionArn": "arn:aws:ecs:us-east-2:113426433733:task-definition/NewFamily:1",
    "containerDefinitions": [
        {
            "name": "my-container",
            "image": "113426433733.dkr.ecr.us-east-2.amazonaws.com/personal:36c842195bc331cbd7a1e51a5e8a1c0def93e9b3",
            "cpu": 0,
            "portMappings": [
                {
                    "name": "my-container-80-tcp",
                    "containerPort": 80,
                    "hostPort": 80,
                    "protocol": "tcp",
                    "appProtocol": "http"
                }
            ],
            "essential": true,
            "environment": [],
            "environmentFiles": [],
            "mountPoints": [],
            "volumesFrom": [],
            "ulimits": [],
            "logConfiguration": {
                "logDriver": "awslogs",
                "options": {
                    "awslogs-create-group": "true",
                    "awslogs-group": "/ecs/NewFamily",
                    "awslogs-region": "us-east-2",
                    "awslogs-stream-prefix": "ecs"
                },
                "secretOptions": []
            }
        }
    ],
    "family": "NewFamily",
    "taskRoleArn": "arn:aws:iam::113426433733:role/ecsTaskExecutionRole",
    "executionRoleArn": "arn:aws:iam::113426433733:role/ecsTaskExecutionRole",
    "networkMode": "awsvpc",
    "revision": 1,
    "volumes": [],
    "status": "ACTIVE",
    "requiresAttributes": [
        {
            "name": "com.amazonaws.ecs.capability.logging-driver.awslogs"
        },
        {
            "name": "ecs.capability.execution-role-awslogs"
        },
        {
            "name": "com.amazonaws.ecs.capability.ecr-auth"
        },
        {
            "name": "com.amazonaws.ecs.capability.docker-remote-api.1.19"
        },
        {
            "name": "com.amazonaws.ecs.capability.task-iam-role"
        },
        {
            "name": "ecs.capability.execution-role-ecr-pull"
        },
        {
            "name": "com.amazonaws.ecs.capability.docker-remote-api.1.18"
        },
        {
            "name": "ecs.capability.task-eni"
        },
        {
            "name": "com.amazonaws.ecs.capability.docker-remote-api.1.29"
        }
    ],
    "placementConstraints": [],
    "compatibilities": [
        "EC2",
        "FARGATE"
    ],
    "requiresCompatibilities": [
        "EC2"
    ],
    "cpu": "1024",
    "memory": "3072",
    "runtimePlatform": {
        "cpuArchitecture": "X86_64",
        "operatingSystemFamily": "LINUX"
    },
    "registeredAt": "2023-09-22T00:56:25.100Z",
    "registeredBy": "arn:aws:iam::113426433733:root",
    "tags": []
}
